agentc_cli/__init__.py
agentc_cli/cmds/__init__.py
agentc_cli/cmds/add.py
agentc_cli/cmds/clean.py
agentc_cli/cmds/env.py
agentc_cli/cmds/execute.py
agentc_cli/cmds/find.py
agentc_cli/cmds/index.py
agentc_cli/cmds/init.py
agentc_cli/cmds/ls.py
agentc_cli/cmds/publish.py
agentc_cli/cmds/status.py
agentc_cli/cmds/util.py
agentc_cli/cmds/version.py
agentc_cli/cmds/web.py
agentc_cli/main.py
agentc_cli/util.py
agentc_cli-0.2.2a1.dist-info/METADATA
agentc_cli-0.2.2a1.dist-info/WHEEL
agentc_cli-0.2.2a1.dist-info/entry_points.txt
agentc_cli-0.2.2a1.dist-info/RECORD
