Metadata-Version: 2.3
Name: agentc-cli
Version: 0.2.2a1
Summary: The command line interface for the Couchbase Agent Catalog project.
License: Apache-2.0
Author: Glenn Galvizo
Author-email: glenn.galvizo@couchbase.com
Requires-Python: >=3.12
Classifier: License :: OSI Approved :: Apache Software License
Classifier: Programming Language :: Python :: 3
Classifier: Programming Language :: Python :: 3.12
Classifier: Programming Language :: Python :: 3.13
Requires-Dist: agentc-core (>=0.0.0,<0.0.1)
Requires-Dist: click-extra (>=4.15.0,<5.0.0)
Requires-Dist: dateparser (>=1.2.0,<2.0.0)
Requires-Dist: tqdm (>=4.66.5,<5.0.0)
Project-URL: Documentation, https://couchbaselabs.github.io/agent-catalog/cli.html
Project-URL: Repository, https://github.com/couchbaselabs/agent-catalog
